jsonvariable/__init__.py
jsonvariable/error.py
jsonvariable/resolver.py
ootz_json_variable-1.0.0.dist-info/LICENSE
ootz_json_variable-1.0.0.dist-info/METADATA
ootz_json_variable-1.0.0.dist-info/WHEEL
ootz_json_variable-1.0.0.dist-info/top_level.txt
ootz_json_variable-1.0.0.dist-info/RECORD
